{"id":"689a0b63-8a3e-4cdb-8802-52a7db48655c","name":"Klee","element":"pyro","rarity":5,"constellation":"Trifolium","weapon_type":"Catalyst","talents":{"normal":{"name":"Normal Attack: Kaboom!","img_url":"img-skills-s_293101.png"},"skill":{"name":"Jumpy Dumpty","img_url":"img-skills-s_293201.png"},"burst":{"name":"Sparks 'n' Splash","img_url":"img-skills-s_293901.png"}},"materials":{"gem":{"green":{"name":"Agnidus Agate Sliver","img_url":"img-upgrade-gem-i_311.png"},"blue":{"name":"Agnidus Agate Fragment","img_url":"img-upgrade-gem-i_312.png"},"pink":{"name":"Agnidus Agate Chunk","img_url":"img-upgrade-gem-i_313.png"},"gold":{"name":"Agnidus Agate Gemstone","img_url":"img-upgrade-gem-i_314.png"}},"natural":{"name":"Philanemo Mushroom","img_url":"img-upgrade-gem-i_607.png"},"boss":{"name":"Everflame Seed","img_url":"img-upgrade-gem-i_201.png"},"mob":{"gray":{"name":"Divining Scroll","img_url":"img-upgrade-material-i_41.png"},"green":{"name":"Sealed Scroll","img_url":"img-upgrade-material-i_42.png"},"blue":{"name":"Forbidden Curse Scroll","img_url":"img-upgrade-material-i_43.png"}},"weekly":{"name":"Ring of Boreas","img_url":"img-upgrade-guide-i_465.png"},"book":{"green":{"name":"Teachings of Freedom","img_url":"img-upgrade-guide-i_421.png"},"blue":{"name":"Guide to Freedom","img_url":"img-upgrade-guide-i_422.png"},"pink":{"name":"Philosophies of Freedom","img_url":"img-upgrade-guide-i_423.png"}}},"background_urls":{"card":"img-char-klee.png","gatcha":"img-char-klee_gacha_splash.png"}}